deepsvp/main.py
deepsvp/model.py
deepsvp-1.0.3.dist-info/LICENSE
deepsvp-1.0.3.dist-info/METADATA
deepsvp-1.0.3.dist-info/WHEEL
deepsvp-1.0.3.dist-info/entry_points.txt
deepsvp-1.0.3.dist-info/top_level.txt
deepsvp-1.0.3.dist-info/zip-safe
deepsvp-1.0.3.dist-info/RECORD
