Metadata-Version: 2.1
Name: deepsvp
Version: 1.0.3
Summary: DeepSVP: Integration of Genomics and Phenotypes forStructural Variant Prioritization using Deep Learning
Home-page: UNKNOWN
Author: Azza Althagafi
Author-email: azza.althagafi@kaust.edu.sa
License: Apache 2.0
Download-URL: https://github.com/bio-ontology-research-group/deepsvp/archive/v1.0.3.tar.gz
Platform: UNKNOWN
Requires-Python: >3
Requires-Dist: click (<8)
Requires-Dist: scikit-learn
Requires-Dist: pandas
Requires-Dist: tensorflow (==2.3.0)
Requires-Dist: numpy
Requires-Dist: scipy
Requires-Dist: gensim (==3.8.3)
Requires-Dist: sklearn
Requires-Dist: mygene
Requires-Dist: h5py
Requires-Dist: progress
